flake8_pytest_fixtures_style/__init__.py
flake8_pytest_fixtures_style/config.py
flake8_pytest_fixtures_style/errors.py
flake8_pytest_fixtures_style/plugin.py
flake8_pytest_fixtures_style/utils.py
flake8_pytest_fixtures_style/visitors.py
tests/__init__.py
tests/test_PF001_fixture_factory.py
tests/test_PF002_unused_fixture.py
tests/test_utils.py
flake8_pytest_fixtures_style-0.0.3.dist-info/LICENSE
flake8_pytest_fixtures_style-0.0.3.dist-info/METADATA
flake8_pytest_fixtures_style-0.0.3.dist-info/WHEEL
flake8_pytest_fixtures_style-0.0.3.dist-info/entry_points.txt
flake8_pytest_fixtures_style-0.0.3.dist-info/top_level.txt
flake8_pytest_fixtures_style-0.0.3.dist-info/RECORD
