Metadata-Version: 2.1
Name: flake8-pytest-fixtures-style
Version: 0.0.3
Summary: A flake8 extension that checks pytest fixtures
Home-page: https://github.com/sidorov-as/flake8-pytest-fixtures-style
Author: Alexey Sidorov
Author-email: ereon.dev@gmail.com
License: MIT
Keywords: flake8
Platform: UNKNOWN
Classifier: Environment :: Console
Classifier: Environment :: Plugins
Classifier: Framework :: Flake8
Classifier: Framework :: Pytest
Classifier: Intended Audience :: Developers
Classifier: Operating System :: OS Independent
Classifier: Topic :: Software Development :: Quality Assurance
Classifier: Topic :: Software Development :: Testing
Classifier: Topic :: Software Development :: Testing :: Unit
Classifier: Programming Language :: Python
Classifier: Programming Language :: Python :: 3.8
Classifier: Programming Language :: Python :: 3.9
Requires-Python: >=3.8
License-File: LICENSE
Requires-Dist: flake8 (<5,>=3)
Requires-Dist: flake8-plugin-utils (==1.3.2)
Requires-Dist: flake8-pytest-style (==1.6.0)
